metaplapi/__init__.py
metaplapi/constant.py
metaplapi/device.py
metaplapi/facebook.py
metaplapi/generator.py
metaplapi/headers.py
metaplapi/identifier.py
metaplapi/instagram.py
metaplapi/threads.py
metaplapi/useragent.py
metaplapi-0.0.2.dist-info/licenses/LICENSE
metaplapi-0.0.2.dist-info/METADATA
metaplapi-0.0.2.dist-info/WHEEL
metaplapi-0.0.2.dist-info/top_level.txt
metaplapi-0.0.2.dist-info/RECORD
