Metadata-Version: 2.4
Name: metaplapi
Version: 0.0.2
Summary: Python Library for Interacting with Meta Platforms Api: Threads, Facebook, and Instagram
Author-email: Moh Iqbal Hidayat <iqbalmh18.dev@gmail.com>
License: MIT License
Project-URL: Homepage, https://pypi.org/project/metaplapi
Project-URL: Source, https://github.com/iqbalmh18/metaplapi
Keywords: meta,metaplapi,threads,threads-api,facebook,facebook-api,instagram,instagram-api
Classifier: Programming Language :: Python :: 3
Classifier: License :: OSI Approved :: MIT License
Classifier: Operating System :: OS Independent
Requires-Python: >=3.7
License-File: LICENSE
Requires-Dist: requests
Requires-Dist: pycryptodomex
Dynamic: license-file
